LICENSE.txt
MANIFEST.in
README.md
pyproject.toml
setup.cfg
setup.py
kartothek/__init__.py
kartothek/api/__init__.py
kartothek/api/consistency.py
kartothek/api/cube.py
kartothek/api/dataset.py
kartothek/api/discover.py
kartothek/api/serialization.py
kartothek/cli/__init__.py
kartothek/cli/_cleanup.py
kartothek/cli/_copy.py
kartothek/cli/_delete.py
kartothek/cli/_index.py
kartothek/cli/_info.py
kartothek/cli/_query.py
kartothek/cli/_stats.py
kartothek/cli/_utils.py
kartothek/core/__init__.py
kartothek/core/_compat.py
kartothek/core/_deprecation.py
kartothek/core/_mixins.py
kartothek/core/_time.py
kartothek/core/_zmsgpack.py
kartothek/core/common_metadata.py
kartothek/core/dataset.py
kartothek/core/docs.py
kartothek/core/factory.py
kartothek/core/index.py
kartothek/core/naming.py
kartothek/core/partition.py
kartothek/core/testing.py
kartothek/core/typing.py
kartothek/core/urlencode.py
kartothek/core/utils.py
kartothek/core/uuid.py
kartothek/core/cube/__init__.py
kartothek/core/cube/conditions.py
kartothek/core/cube/constants.py
kartothek/core/cube/cube.py
kartothek/io/__init__.py
kartothek/io/eager.py
kartothek/io/eager_cube.py
kartothek/io/iter.py
kartothek/io/dask/__init__.py
kartothek/io/dask/_shuffle.py
kartothek/io/dask/_sizeof.py
kartothek/io/dask/_utils.py
kartothek/io/dask/bag.py
kartothek/io/dask/bag_cube.py
kartothek/io/dask/common_cube.py
kartothek/io/dask/compression.py
kartothek/io/dask/dataframe.py
kartothek/io/dask/dataframe_cube.py
kartothek/io/dask/delayed.py
kartothek/io/testing/__init__.py
kartothek/io/testing/append_cube.py
kartothek/io/testing/build_cube.py
kartothek/io/testing/cleanup_cube.py
kartothek/io/testing/copy_cube.py
kartothek/io/testing/delete.py
kartothek/io/testing/delete_cube.py
kartothek/io/testing/extend_cube.py
kartothek/io/testing/gc.py
kartothek/io/testing/index.py
kartothek/io/testing/query_cube.py
kartothek/io/testing/read.py
kartothek/io/testing/stats_cube.py
kartothek/io/testing/update.py
kartothek/io/testing/update_cube.py
regallager.egg-info/PKG-INFO
regallager.egg-info/SOURCES.txt
regallager.egg-info/dependency_links.txt
regallager.egg-info/entry_points.txt
regallager.egg-info/requires.txt
regallager.egg-info/top_level.txt